metareid/__init__.py
metareid/app/__init__.py
metareid/app/onnx_to_trt.py
metareid/app/reid_inference_trt.py
metareid/model_zoo/__init__.py
metareid/model_zoo/trt_engine.py
metareid/model_zoo/trt_export.py
metareid/utils/__init__.py
metareid/utils/general.py
metareid/utils/image_batch.py
meta_reid-5.3.24.dist-info/METADATA
meta_reid-5.3.24.dist-info/WHEEL
meta_reid-5.3.24.dist-info/top_level.txt
meta_reid-5.3.24.dist-info/zip-safe
meta_reid-5.3.24.dist-info/RECORD
