Metadata-Version: 2.1
Name: meta-reid
Version: 5.3.24
Summary: Meta Reid Toolkit
Home-page: https://github.com/CachCheng/cvreid
Author: CachCheng
Author-email: tkggpdc2007@163.com
License: Apache-2.0
Requires-Dist: opencv-python
Requires-Dist: setuptools
Requires-Dist: tensorrt
Requires-Dist: pycuda
Requires-Dist: numpy
Requires-Dist: pillow
Requires-Dist: tqdm
